jupyter_theme_christmas/.DS_Store
jupyter_theme_christmas/__init__.py
jupyter_theme_christmas/_version.py
jupyter_theme_christmas/labextension/package.json
jupyter_theme_christmas/labextension/static/549.c72471b900706114811e.js
jupyter_theme_christmas/labextension/static/568.822def9ece6bdd0eaa9f.js
jupyter_theme_christmas/labextension/static/remoteEntry.f172a1158835546dbf3a.js
jupyter_theme_christmas/labextension/static/style.js
jupyter_theme_christmas/labextension/static/third-party-licenses.json
jupyter_theme_christmas/labextension/themes/@datalayer/jupyter-theme-christmas/index.css
jupyter_theme_christmas/labextension/themes/@datalayer/jupyter-theme-christmas/index.js
jupyter_theme_christmas-0.0.1.data/data/share/jupyter/labextensions/@datalayer/jupyter-theme-christmas/install.json
jupyter_theme_christmas-0.0.1.data/data/share/jupyter/labextensions/@datalayer/jupyter-theme-christmas/package.json
jupyter_theme_christmas-0.0.1.data/data/share/jupyter/labextensions/@datalayer/jupyter-theme-christmas/static/549.c72471b900706114811e.js
jupyter_theme_christmas-0.0.1.data/data/share/jupyter/labextensions/@datalayer/jupyter-theme-christmas/static/568.822def9ece6bdd0eaa9f.js
jupyter_theme_christmas-0.0.1.data/data/share/jupyter/labextensions/@datalayer/jupyter-theme-christmas/static/remoteEntry.f172a1158835546dbf3a.js
jupyter_theme_christmas-0.0.1.data/data/share/jupyter/labextensions/@datalayer/jupyter-theme-christmas/static/style.js
jupyter_theme_christmas-0.0.1.data/data/share/jupyter/labextensions/@datalayer/jupyter-theme-christmas/static/third-party-licenses.json
jupyter_theme_christmas-0.0.1.data/data/share/jupyter/labextensions/@datalayer/jupyter-theme-christmas/themes/@datalayer/jupyter-theme-christmas/index.css
jupyter_theme_christmas-0.0.1.data/data/share/jupyter/labextensions/@datalayer/jupyter-theme-christmas/themes/@datalayer/jupyter-theme-christmas/index.js
jupyterlab_theme_christmas/__init__.py
jupyterlab_theme_christmas/_version.py
jupyter_theme_christmas-0.0.1.dist-info/LICENSE
jupyter_theme_christmas-0.0.1.dist-info/METADATA
jupyter_theme_christmas-0.0.1.dist-info/WHEEL
jupyter_theme_christmas-0.0.1.dist-info/top_level.txt
jupyter_theme_christmas-0.0.1.dist-info/RECORD
