Metadata-Version: 2.1
Name: jupyter-theme-christmas
Version: 0.0.1
Summary: JupyterLab Theme Christmas, Designed by Isabela Presedo-Floyd
Home-page: https://github.com/datalayer/jupyter-theme-christmas
Author: Eric Charles; Isabela Presedo-Floyd
License: BSD-3-Clause
Keywords: Jupyter,JupyterLab,JupyterLab3
Platform: Linux
Platform: Mac OS X
Platform: Windows
Classifier: License :: OSI Approved :: BSD License
Classifier: Programming Language :: Python
Classifier: Programming Language :: Python :: 3
Classifier: Programming Language :: Python :: 3.6
Classifier: Programming Language :: Python :: 3.7
Classifier: Programming Language :: Python :: 3.8
Classifier: Framework :: Jupyter
Requires-Python: >=3.6
License-File: LICENSE
Requires-Dist: jupyterlab (==4.0.0a27)
